session_favorites/__init__.py
session_favorites/apps.py
session_favorites/classes.py
session_favorites/context_processors.py
session_favorites/middleware.py
session_favorites/tests.py
session_favorites/urls.py
session_favorites/views.py
django_session_favorites-1.0.3.dist-info/LICENSE
django_session_favorites-1.0.3.dist-info/METADATA
django_session_favorites-1.0.3.dist-info/WHEEL
django_session_favorites-1.0.3.dist-info/top_level.txt
django_session_favorites-1.0.3.dist-info/RECORD
