Metadata-Version: 2.1
Name: django-session-favorites
Version: 1.0.3
Summary: session_favorites
Home-page: UNKNOWN
Author: Arseny Sysolyatin
Author-email: arseny.sysolyatin@gmail.com
License: UNKNOWN
Platform: UNKNOWN
Classifier: Framework :: Django
Requires-Dist: django (>=1.11)
